live_trade_bench/__init__.py
live_trade_bench/accounts/__init__.py
live_trade_bench/accounts/action.py
live_trade_bench/accounts/base_account.py
live_trade_bench/accounts/polymarket_account.py
live_trade_bench/accounts/stock_account.py
live_trade_bench/accounts/utils.py
live_trade_bench/agents/__init__.py
live_trade_bench/agents/base_agent.py
live_trade_bench/agents/polymarket_agent.py
live_trade_bench/agents/polymarket_system.py
live_trade_bench/agents/stock_agent.py
live_trade_bench/agents/stock_system.py
live_trade_bench/fetchers/__init__.py
live_trade_bench/fetchers/base_fetcher.py
live_trade_bench/fetchers/news_fetcher.py
live_trade_bench/fetchers/option_fetcher.py
live_trade_bench/fetchers/polymarket_fetcher.py
live_trade_bench/fetchers/reddit_fetcher.py
live_trade_bench/fetchers/stock_fetcher.py
live_trade_bench/utils/__init__.py
live_trade_bench/utils/llm_client.py
live_trade_bench/utils/logger.py
live_trade_bench-0.0.1b0.dist-info/LICENSE
live_trade_bench-0.0.1b0.dist-info/METADATA
live_trade_bench-0.0.1b0.dist-info/WHEEL
live_trade_bench-0.0.1b0.dist-info/RECORD
