Metadata-Version: 2.3
Name: live-trade-bench
Version: 0.0.1b0
Summary: Live evaluation of trading agents
License: MIT
Author: Haofei Yu
Author-email: yuhaofei44@gmail.com
Requires-Python: >=3.9,<3.12
Classifier: License :: OSI Approved :: MIT License
Classifier: Programming Language :: Python :: 3
Classifier: Programming Language :: Python :: 3.9
Classifier: Programming Language :: Python :: 3.10
Classifier: Programming Language :: Python :: 3.11
Requires-Dist: beartype (>=0.17.1,<0.18.0)
Requires-Dist: beautifulsoup4
Requires-Dist: fastapi
Requires-Dist: finnhub-python
Requires-Dist: mypy (>=1.16.1,<2.0.0)
Requires-Dist: praw
Requires-Dist: pydantic (>=2.11.7,<3.0.0)
Requires-Dist: requests
Requires-Dist: scipy
Requires-Dist: tenacity
Requires-Dist: uvicorn
Requires-Dist: yfinance
